[
{"term":"샹강","definitions":["중국 홍콩섬 북쪽 기슭에 있는 항구 도시. 해군 기지가 있으며, 중계 가공 무역지로 섬유와 금속을 비롯하여 텅스텐, 차[茶], 비단 따위를 실어 낸다."],"source":"stdict","senses":[{"sense_code":"535897","type":["일반어","동의어"],"definition":"중국 홍콩섬 북쪽 기슭에 있는 항구 도시. 해군 기지가 있으며, 중계 가공 무역지로 섬유와 금속을 비롯하여 텅스텐, 차[茶], 비단 따위를 실어 낸다.","definition_original":"중국 홍콩섬 북쪽 기슭에 있는 항구 도시. 해군 기지가 있으며, 중계 가공 무역지로 섬유와 금속을 비롯하여 텅스텐, 차[茶], 비단 따위를 실어 낸다.","cat":"지명","word":"홍콩","unit":"의미","link_target_code":"68885","link":"https://stdict.korean.go.kr/search/searchView.do?word_no=505023&searchKeywordTo=3"}],"attrs":{"wordInfo":{"word":["샹강","홍콩"],"word_unit":"단어","word_type":"외래어","original_language":"Xianggang[香港]","language_type":"안 밝힘","pos_code":"180627001","pos":"명사","comm_pattern_code":"180627001001","sense_code":"535897","type":["일반어","동의어"],"definition":"중국 홍콩섬 북쪽 기슭에 있는 항구 도시. 해군 기지가 있으며, 중계 가공 무역지로 섬유와 금속을 비롯하여 텅스텐, 차[茶], 비단 따위를 실어 낸다.","definition_original":"중국 홍콩섬 북쪽 기슭에 있는 항구 도시. 해군 기지가 있으며, 중계 가공 무역지로 섬유와 금속을 비롯하여 텅스텐, 차[茶], 비단 따위를 실어 낸다.","cat":"지명","unit":"의미","link_target_code":"68885","link":"https://stdict.korean.go.kr/search/searchView.do?word_no=505023&searchKeywordTo=3"}}},
{"term":"샹들리에","definitions":["천장에 매달아 드리우게 된, 여러 개의 가지가 달린 방사형 모양의 등(燈). 가지 끝마다 불을 켜는데 예전에는 촛불이나 가스등을 켰으나 지금은 주로 전등을 켠다."],"source":"stdict","senses":[{"sense_code":"192785","type":["일반어","사진","사진","동의어"],"definition":"천장에 매달아 드리우게 된, 여러 개의 가지가 달린 방사형 모양의 등(燈). 가지 끝마다 불을 켜는데 예전에는 촛불이나 가스등을 켰으나 지금은 주로 전등을 켠다.","definition_original":"천장에 매달아 드리우게 된, 여러 개의 가지가 달린 방사형 모양의 등(燈). 가지 끝마다 불을 켜는데 예전에는 촛불이나 가스등을 켰으나 지금은 주로 전등을 켠다.","example":"그 연회장에는 휘황찬란한 샹들리에가 천장에 매달려 불빛을 밝히고 있었으며 바닥에는 붉은 양탄자가 깔려 있었다.","link":["http://media.korean.go.kr/front/view/mediaView.do?file_no=196567","http://media.korean.go.kr/front/view/mediaView.do?file_no=196568","https://stdict.korean.go.kr/search/searchView.do?word_no=351761&searchKeywordTo=3"],"word":"펜던트","unit":"의미","link_target_code":"58720"}],"attrs":{"wordInfo":{"word":["샹들리에","펜던트"],"word_unit":"단어","word_type":"외래어","original_language":"chandelier","language_type":"프랑스어","pos_code":"438981001","pos":"명사","comm_pattern_code":"438981001001","sense_code":"192785","type":["일반어","사진","사진","동의어"],"definition":"천장에 매달아 드리우게 된, 여러 개의 가지가 달린 방사형 모양의 등(燈). 가지 끝마다 불을 켜는데 예전에는 촛불이나 가스등을 켰으나 지금은 주로 전등을 켠다.","definition_original":"천장에 매달아 드리우게 된, 여러 개의 가지가 달린 방사형 모양의 등(燈). 가지 끝마다 불을 켜는데 예전에는 촛불이나 가스등을 켰으나 지금은 주로 전등을 켠다.","example":"그 연회장에는 휘황찬란한 샹들리에가 천장에 매달려 불빛을 밝히고 있었으며 바닥에는 붉은 양탄자가 깔려 있었다.","link":["http://media.korean.go.kr/front/view/mediaView.do?file_no=196567","http://media.korean.go.kr/front/view/mediaView.do?file_no=196568","https://stdict.korean.go.kr/search/searchView.do?word_no=351761&searchKeywordTo=3"],"unit":"의미","link_target_code":"58720"}}},
{"term":"샹보르-성","definitions":["프랑스 중부의 루아르강 유역에 있는 성. 프랑수아 일세의 명으로 1536년에 완성된 초기 르네상스 건축물로 네 모퉁이에 탑이 있는 사각형 건물이다."],"source":"stdict","senses":[{"sense_code":"572661","type":"일반어","definition":"프랑스 중부의 루아르강 유역에 있는 성. 프랑수아 일세의 명으로 1536년에 완성된 초기 르네상스 건축물로 네 모퉁이에 탑이 있는 사각형 건물이다.","definition_original":"프랑스 중부의 루아르강 유역에 있는 성. 프랑수아 일세의 명으로 1536년에 완성된 초기 르네상스 건축물로 네 모퉁이에 탑이 있는 사각형 건물이다.","cat":"역사"}],"attrs":{"wordInfo":{"word":"샹보르-성","word_unit":"단어","word_type":"혼종어","original_language":["Chambord","城"],"language_type":["안 밝힘","한자"],"pos_code":"180632001","pos":"명사","comm_pattern_code":"180632001001","sense_code":"572661","type":"일반어","definition":"프랑스 중부의 루아르강 유역에 있는 성. 프랑수아 일세의 명으로 1536년에 완성된 초기 르네상스 건축물로 네 모퉁이에 탑이 있는 사각형 건물이다.","definition_original":"프랑스 중부의 루아르강 유역에 있는 성. 프랑수아 일세의 명으로 1536년에 완성된 초기 르네상스 건축물로 네 모퉁이에 탑이 있는 사각형 건물이다.","cat":"역사"}}},
{"term":"샹송01","definitions":["프랑스의 소설가(1900~1984). 1930년대의 대표적 좌익 지식인으로, 사회와 인간의 자유 문제를 다루었다. 작품에 <징역선(懲役船)>, <최후의 마을> 따위가 있다."],"source":"stdict","senses":[{"sense_code":"192788","type":"일반어","definition":"프랑스의 소설가(1900~1984). 1930년대의 대표적 좌익 지식인으로, 사회와 인간의 자유 문제를 다루었다. 작품에 <징역선(懲役船)>, <최후의 마을> 따위가 있다.","definition_original":"프랑스의 소설가(1900~1984). 1930년대의 대표적 좌익 지식인으로, 사회와 인간의 자유 문제를 다루었다. 작품에 <징역선(懲役船)>, <최후의 마을> 따위가 있다.","cat":"인명"}],"attrs":{"wordInfo":{"word":"샹송01","word_unit":"단어","word_type":"외래어","original_language":"Chamson, André","language_type":"안 밝힘","pos_code":"439154001","pos":"명사","comm_pattern_code":"439154001001","sense_code":"192788","type":"일반어","definition":"프랑스의 소설가(1900~1984). 1930년대의 대표적 좌익 지식인으로, 사회와 인간의 자유 문제를 다루었다. 작품에 <징역선(懲役船)>, <최후의 마을> 따위가 있다.","definition_original":"프랑스의 소설가(1900~1984). 1930년대의 대표적 좌익 지식인으로, 사회와 인간의 자유 문제를 다루었다. 작품에 <징역선(懲役船)>, <최후의 마을> 따위가 있다.","cat":"인명"}}},
{"term":"샹송02","definitions":["프랑스 대중 사이에서 널리 불리는 가요. 가사의 내용이 중요시되며, 쿠플레(couplet)라고 하는 이야기체 부분과 르프랭(refrain)이라고 하는 반복 부분으로 되어 있다."],"source":"stdict","senses":[{"sense_code":"535898","type":"일반어","definition":"프랑스 대중 사이에서 널리 불리는 가요. 가사의 내용이 중요시되며, 쿠플레(couplet)라고 하는 이야기체 부분과 르프랭(refrain)이라고 하는 반복 부분으로 되어 있다.","definition_original":"프랑스 대중 사이에서 널리 불리는 가요. 가사의 내용이 중요시되며, 쿠플레(couplet)라고 하는 이야기체 부분과 르프랭(refrain)이라고 하는 반복 부분으로 되어 있다.","cat":"음악"}],"attrs":{"wordInfo":{"word":"샹송02","word_unit":"단어","word_type":"외래어","original_language":"chanson","language_type":"프랑스어","pos_code":"180327001","pos":"명사","comm_pattern_code":"180327001001","sense_code":"535898","type":"일반어","definition":"프랑스 대중 사이에서 널리 불리는 가요. 가사의 내용이 중요시되며, 쿠플레(couplet)라고 하는 이야기체 부분과 르프랭(refrain)이라고 하는 반복 부분으로 되어 있다.","definition_original":"프랑스 대중 사이에서 널리 불리는 가요. 가사의 내용이 중요시되며, 쿠플레(couplet)라고 하는 이야기체 부분과 르프랭(refrain)이라고 하는 반복 부분으로 되어 있다.","cat":"음악"}}},
{"term":"샹슬라드-인","definitions":["1888년에 프랑스의 서남쪽 샹슬라드 지방의 레이몽당 유적의 막달레니앙 문화층에서 발견된 원시인의 유골 화석. 구석기 말기에 속하는 것으로, 크로마뇽인의 형태적 변이에 속하는 특징을 보인다."],"source":"stdict","senses":[{"sense_code":"192789","type":"일반어","definition":"1888년에 프랑스의 서남쪽 샹슬라드 지방의 레이몽당 유적의 막달레니앙 문화층에서 발견된 원시인의 유골 화석. 구석기 말기에 속하는 것으로, 크로마뇽인의 형태적 변이에 속하는 특징을 보인다.","definition_original":"1888년에 프랑스의 서남쪽 샹슬라드 지방의 레이몽당 유적의 막달레니앙 문화층에서 발견된 원시인의 유골 화석. 구석기 말기에 속하는 것으로, 크로마뇽인의 형태적 변이에 속하는 특징을 보인다.","cat":"역사"}],"attrs":{"wordInfo":{"word":"샹슬라드-인","word_unit":"단어","word_type":"혼종어","original_language":["Chancelade","人"],"language_type":["안 밝힘","한자"],"pos_code":"180328001","pos":"명사","comm_pattern_code":"180328001001","sense_code":"192789","type":"일반어","definition":"1888년에 프랑스의 서남쪽 샹슬라드 지방의 레이몽당 유적의 막달레니앙 문화층에서 발견된 원시인의 유골 화석. 구석기 말기에 속하는 것으로, 크로마뇽인의 형태적 변이에 속하는 특징을 보인다.","definition_original":"1888년에 프랑스의 서남쪽 샹슬라드 지방의 레이몽당 유적의 막달레니앙 문화층에서 발견된 원시인의 유골 화석. 구석기 말기에 속하는 것으로, 크로마뇽인의 형태적 변이에 속하는 특징을 보인다.","cat":"역사"}}},
{"term":"샹양","definitions":["중국 후베이성(湖北省) 북부에 있는 도시. 상업이 발달하였고 교통이 편리하다. 상업 중심지로 상품의 집산지이며, 식용유·직물·유리 따위를 생산한다."],"source":"stdict","senses":[{"sense_code":"192791","type":"일반어","definition":"중국 후베이성(湖北省) 북부에 있는 도시. 상업이 발달하였고 교통이 편리하다. 상업 중심지로 상품의 집산지이며, 식용유·직물·유리 따위를 생산한다.","definition_original":"중국 후베이성(湖北省) 북부에 있는 도시. 상업이 발달하였고 교통이 편리하다. 상업 중심지로 상품의 집산지이며, 식용유·직물·유리 따위를 생산한다.","cat":"지명"}],"attrs":{"wordInfo":{"word":"샹양","word_unit":"단어","word_type":"외래어","original_language":"Xiangyang[襄陽]","language_type":"안 밝힘","pos_code":"180937001","pos":"명사","comm_pattern_code":"180937001001","sense_code":"192791","type":"일반어","definition":"중국 후베이성(湖北省) 북부에 있는 도시. 상업이 발달하였고 교통이 편리하다. 상업 중심지로 상품의 집산지이며, 식용유·직물·유리 따위를 생산한다.","definition_original":"중국 후베이성(湖北省) 북부에 있는 도시. 상업이 발달하였고 교통이 편리하다. 상업 중심지로 상품의 집산지이며, 식용유·직물·유리 따위를 생산한다.","cat":"지명"}}},
{"term":"샹저우","definitions":["중국 후베이성(湖北省) 북부에 있는 마을. 샹양시(襄陽市)의 구(區)이다. 예로부터 군사 요충지였다."],"source":"stdict","senses":[{"sense_code":"769808","type":"일반어","definition":"중국 후베이성(湖北省) 북부에 있는 마을. 샹양시(襄陽市)의 구(區)이다. 예로부터 군사 요충지였다.","definition_original":"중국 후베이성(湖北省) 북부에 있는 마을. 샹양시(襄陽市)의 구(區)이다. 예로부터 군사 요충지였다.","cat":"지명"}],"attrs":{"wordInfo":{"word":"샹저우","word_unit":"단어","word_type":"외래어","original_language":"Xiangzhou[襄州]","language_type":"안 밝힘","pos_code":"518474001","pos":"명사","comm_pattern_code":"518474001001","sense_code":"769808","type":"일반어","definition":"중국 후베이성(湖北省) 북부에 있는 마을. 샹양시(襄陽市)의 구(區)이다. 예로부터 군사 요충지였다.","definition_original":"중국 후베이성(湖北省) 북부에 있는 마을. 샹양시(襄陽市)의 구(區)이다. 예로부터 군사 요충지였다.","cat":"지명"}}},
{"term":"샹젤리제","definitions":["프랑스 파리에 있는 간선 도로의 하나. 개선문이 있는 드골 광장에서 콩코르드 광장에 이르는 직선 도로로, 양쪽에는 마로니에와 플라타너스 따위의 가로수와 함께 호텔·고급 상점·카페 따위가 줄지어 있으며, 대통령 관저로 사용되는 엘리제 궁전을 비롯하여 산책로가 있는 공원이 유명하다. 길이는 1,880미터."],"source":"stdict","senses":[{"sense_code":"388657","type":"일반어","definition":"프랑스 파리에 있는 간선 도로의 하나. 개선문이 있는 드골 광장에서 콩코르드 광장에 이르는 직선 도로로, 양쪽에는 마로니에와 플라타너스 따위의 가로수와 함께 호텔·고급 상점·카페 따위가 줄지어 있으며, 대통령 관저로 사용되는 엘리제 궁전을 비롯하여 산책로가 있는 공원이 유명하다. 길이는 1,880미터.","definition_original":"프랑스 파리에 있는 간선 도로의 하나. 개선문이 있는 드골 광장에서 콩코르드 광장에 이르는 직선 도로로, 양쪽에는 마로니에와 플라타너스 따위의 가로수와 함께 호텔·고급 상점·카페 따위가 줄지어 있으며, 대통령 관저로 사용되는 엘리제 궁전을 비롯하여 산책로가 있는 공원이 유명하다. 길이는 1,880미터.","cat":"지명"}],"attrs":{"wordInfo":{"word":"샹젤리제","word_unit":"단어","word_type":"외래어","original_language":"Champs-Élysées","language_type":"안 밝힘","pos_code":"439241001","pos":"명사","comm_pattern_code":"439241001001","sense_code":"388657","type":"일반어","definition":"프랑스 파리에 있는 간선 도로의 하나. 개선문이 있는 드골 광장에서 콩코르드 광장에 이르는 직선 도로로, 양쪽에는 마로니에와 플라타너스 따위의 가로수와 함께 호텔·고급 상점·카페 따위가 줄지어 있으며, 대통령 관저로 사용되는 엘리제 궁전을 비롯하여 산책로가 있는 공원이 유명하다. 길이는 1,880미터.","definition_original":"프랑스 파리에 있는 간선 도로의 하나. 개선문이 있는 드골 광장에서 콩코르드 광장에 이르는 직선 도로로, 양쪽에는 마로니에와 플라타너스 따위의 가로수와 함께 호텔·고급 상점·카페 따위가 줄지어 있으며, 대통령 관저로 사용되는 엘리제 궁전을 비롯하여 산책로가 있는 공원이 유명하다. 길이는 1,880미터.","cat":"지명"}}},
{"term":"샹카라","definitions":["인도의 철학자(700~750). 불이일원론파(不二一元論派)의 개조이며, 저서에 ≪브라흐마수트라 주해(Brahma-sutra註解)≫가 있다."],"source":"stdict","senses":[{"sense_code":"425374","type":"일반어","definition":"인도의 철학자(700~750). 불이일원론파(不二一元論派)의 개조이며, 저서에 ≪브라흐마수트라 주해(Brahma-sutra註解)≫가 있다.","definition_original":"인도의 철학자(700~750). 불이일원론파(不二一元論派)의 개조이며, 저서에 ≪브라흐마수트라 주해(Brahma-sutra註解)≫가 있다.","cat":"인명"}],"attrs":{"wordInfo":{"word":"샹카라","word_unit":"단어","word_type":"외래어","original_language":"Śa<EQU>ṅ</EQU>kara","language_type":"안 밝힘","pos_code":"180941001","pos":"명사","comm_pattern_code":"180941001001","sense_code":"425374","type":"일반어","definition":"인도의 철학자(700~750). 불이일원론파(不二一元論派)의 개조이며, 저서에 ≪브라흐마수트라 주해(Brahma-sutra註解)≫가 있다.","definition_original":"인도의 철학자(700~750). 불이일원론파(不二一元論派)의 개조이며, 저서에 ≪브라흐마수트라 주해(Brahma-sutra註解)≫가 있다.","cat":"인명"}}},
{"term":"샹탄","definitions":["중국 후난성(湖南省) 동부, 샹장강(湘江江) 하류에 있는 도시. 수륙 교통의 요지로, 농산물의 집산지이며 기계·방직·시멘트 따위의 공업이 발달하였다."],"source":"stdict","senses":[{"sense_code":"193009","type":"일반어","definition":"중국 후난성(湖南省) 동부, 샹장강(湘江江) 하류에 있는 도시. 수륙 교통의 요지로, 농산물의 집산지이며 기계·방직·시멘트 따위의 공업이 발달하였다.","definition_original":"중국 후난성(湖南省) 동부, 샹장강(湘江江) 하류에 있는 도시. 수륙 교통의 요지로, 농산물의 집산지이며 기계·방직·시멘트 따위의 공업이 발달하였다.","cat":"지명"}],"attrs":{"wordInfo":{"word":"샹탄","word_unit":"단어","word_type":"외래어","original_language":"Xiangtan[湘潭]","language_type":"안 밝힘","pos_code":"180942001","pos":"명사","comm_pattern_code":"180942001001","sense_code":"193009","type":"일반어","definition":"중국 후난성(湖南省) 동부, 샹장강(湘江江) 하류에 있는 도시. 수륙 교통의 요지로, 농산물의 집산지이며 기계·방직·시멘트 따위의 공업이 발달하였다.","definition_original":"중국 후난성(湖南省) 동부, 샹장강(湘江江) 하류에 있는 도시. 수륙 교통의 요지로, 농산물의 집산지이며 기계·방직·시멘트 따위의 공업이 발달하였다.","cat":"지명"}}},
{"term":"샹파뉴01","definitions":["프랑스 동북부에 있는 주. 세계적인 포도주 산지로 유명하며, 야금·섬유 공업이 발달하였다. 중심 도시는 트루아이다."],"source":"stdict","senses":[{"sense_code":"499197","type":"일반어","definition":"프랑스 동북부에 있는 주. 세계적인 포도주 산지로 유명하며, 야금·섬유 공업이 발달하였다. 중심 도시는 트루아이다.","definition_original":"프랑스 동북부에 있는 주. 세계적인 포도주 산지로 유명하며, 야금·섬유 공업이 발달하였다. 중심 도시는 트루아이다.","cat":"지명"}],"attrs":{"wordInfo":{"word":"샹파뉴01","word_unit":"단어","word_type":"외래어","original_language":"Champagne","language_type":"안 밝힘","pos_code":"439242001","pos":"명사","comm_pattern_code":"439242001001","sense_code":"499197","type":"일반어","definition":"프랑스 동북부에 있는 주. 세계적인 포도주 산지로 유명하며, 야금·섬유 공업이 발달하였다. 중심 도시는 트루아이다.","definition_original":"프랑스 동북부에 있는 주. 세계적인 포도주 산지로 유명하며, 야금·섬유 공업이 발달하였다. 중심 도시는 트루아이다.","cat":"지명"}}},
{"term":"샹파뉴02","definitions":["프랑스의 화가(1602~1674). 루이 십삼세의 궁정 화가가 되어 종교화, 초상화 분야에서 활약하였다. 작품에 <루이 십삼세 상(像)>이 있다."],"source":"stdict","senses":[{"sense_code":"193011","type":"일반어","definition":"프랑스의 화가(1602~1674). 루이 십삼세의 궁정 화가가 되어 종교화, 초상화 분야에서 활약하였다. 작품에 <루이 십삼세 상(像)>이 있다.","definition_original":"프랑스의 화가(1602~1674). 루이 십삼세의 궁정 화가가 되어 종교화, 초상화 분야에서 활약하였다. 작품에 <루이 십삼세 상(像)>이 있다.","cat":"인명"}],"attrs":{"wordInfo":{"word":"샹파뉴02","word_unit":"단어","word_type":"외래어","original_language":"Champaigne, Philippe de","language_type":"안 밝힘","pos_code":"180944001","pos":"명사","comm_pattern_code":"180944001001","sense_code":"193011","type":"일반어","definition":"프랑스의 화가(1602~1674). 루이 십삼세의 궁정 화가가 되어 종교화, 초상화 분야에서 활약하였다. 작품에 <루이 십삼세 상(像)>이 있다.","definition_original":"프랑스의 화가(1602~1674). 루이 십삼세의 궁정 화가가 되어 종교화, 초상화 분야에서 활약하였다. 작품에 <루이 십삼세 상(像)>이 있다.","cat":"인명"}}},
{"term":"샹폴리옹","definitions":["프랑스의 이집트학자(1790~1832). 1822년에 로제타석에 새겨져 있는 이집트 상형 문자를 처음으로 해독하였다."],"source":"stdict","senses":[{"sense_code":"352229","type":"일반어","definition":"프랑스의 이집트학자(1790~1832). 1822년에 로제타석에 새겨져 있는 이집트 상형 문자를 처음으로 해독하였다.","definition_original":"프랑스의 이집트학자(1790~1832). 1822년에 로제타석에 새겨져 있는 이집트 상형 문자를 처음으로 해독하였다.","cat":"인명"}],"attrs":{"wordInfo":{"word":"샹폴리옹","word_unit":"단어","word_type":"외래어","original_language":"Champollion, Jean François","language_type":"안 밝힘","pos_code":"439421001","pos":"명사","comm_pattern_code":"439421001001","sense_code":"352229","type":"일반어","definition":"프랑스의 이집트학자(1790~1832). 1822년에 로제타석에 새겨져 있는 이집트 상형 문자를 처음으로 해독하였다.","definition_original":"프랑스의 이집트학자(1790~1832). 1822년에 로제타석에 새겨져 있는 이집트 상형 문자를 처음으로 해독하였다.","cat":"인명"}}},
{"term":"샹플랭","definitions":["프랑스의 탐험가(1567~1635). 캐나다를 탐험하여 퀘벡 식민지의 경영에 힘썼고 후에 캐나다 총독이 되었다."],"source":"stdict","senses":[{"sense_code":"535916","type":"일반어","definition":"프랑스의 탐험가(1567~1635). 캐나다를 탐험하여 퀘벡 식민지의 경영에 힘썼고 후에 캐나다 총독이 되었다.","definition_original":"프랑스의 탐험가(1567~1635). 캐나다를 탐험하여 퀘벡 식민지의 경영에 힘썼고 후에 캐나다 총독이 되었다.","cat":"인명"}],"attrs":{"wordInfo":{"word":"샹플랭","word_unit":"단어","word_type":"외래어","original_language":"Champlain, Samuel de","language_type":"안 밝힘","pos_code":"181213001","pos":"명사","comm_pattern_code":"181213001001","sense_code":"535916","type":"일반어","definition":"프랑스의 탐험가(1567~1635). 캐나다를 탐험하여 퀘벡 식민지의 경영에 힘썼고 후에 캐나다 총독이 되었다.","definition_original":"프랑스의 탐험가(1567~1635). 캐나다를 탐험하여 퀘벡 식민지의 경영에 힘썼고 후에 캐나다 총독이 되었다.","cat":"인명"}}},
{"term":"샹플뢰리","definitions":["프랑스의 소설가(1821~1889). 본명은 쥘 플뢰리 위송(Jules Fleury Husson). 사실주의를 주창하였고, 작품에 <시앵카유>가 있다."],"source":"stdict","senses":[{"sense_code":"193012","type":"일반어","definition":"프랑스의 소설가(1821~1889). 본명은 쥘 플뢰리 위송(Jules Fleury Husson). 사실주의를 주창하였고, 작품에 <시앵카유>가 있다.","definition_original":"프랑스의 소설가(1821~1889). 본명은 쥘 플뢰리 위송(Jules Fleury Husson). 사실주의를 주창하였고, 작품에 <시앵카유>가 있다.","cat":"인명"}],"attrs":{"wordInfo":{"word":"샹플뢰리","word_unit":"단어","word_type":"외래어","original_language":"Champfleury","language_type":"안 밝힘","pos_code":"439422001","pos":"명사","comm_pattern_code":"439422001001","sense_code":"193012","type":"일반어","definition":"프랑스의 소설가(1821~1889). 본명은 쥘 플뢰리 위송(Jules Fleury Husson). 사실주의를 주창하였고, 작품에 <시앵카유>가 있다.","definition_original":"프랑스의 소설가(1821~1889). 본명은 쥘 플뢰리 위송(Jules Fleury Husson). 사실주의를 주창하였고, 작품에 <시앵카유>가 있다.","cat":"인명"}}}
]
